{
  "id": "daaada8b-29a2-4299-8a97-1a617808530a",
  "prevId": "00000000-0000-0000-0000-000000000000",
  "version": "7",
  "dialect": "postgresql",
  "tables": {
    "public.articles": {
      "name": "articles",
      "schema": "",
      "columns": {
        "id": {
          "name": "id",
          "type": "serial",
          "primaryKey": true,
          "notNull": true
        },
        "title": {
          "name": "title",
          "type": "text",
          "primaryKey": false,
          "notNull": true
        },
        "description": {
          "name": "description",
          "type": "text",
          "primaryKey": false,
          "notNull": true
        },
        "content": {
          "name": "content",
          "type": "text",
          "primaryKey": false,
          "notNull": true
        },
        "citations": {
          "name": "citations",
          "type": "json",
          "primaryKey": false,
          "notNull": false
        }
      },
      "indexes": {},
      "foreignKeys": {},
      "compositePrimaryKeys": {},
      "uniqueConstraints": {},
      "policies": {},
      "checkConstraints": {},
      "isRLSEnabled": false
    }
  },
  "enums": {},
  "schemas": {},
  "sequences": {},
  "roles": {},
  "policies": {},
  "views": {},
  "_meta": {
    "columns": {},
    "schemas": {},
    "tables": {}
  }
}